kosciuszko/__init__.py
kosciuszko_addfile/__init__.py
kosciuszko_extract/__init__.py
kosciuszko_extract_file/__init__.py
kosciuszko_list/__init__.py
kosciuszko_new/__init__.py
kosciuszko_utils-0.2.0.dist-info/LICENSE
kosciuszko_utils-0.2.0.dist-info/METADATA
kosciuszko_utils-0.2.0.dist-info/WHEEL
kosciuszko_utils-0.2.0.dist-info/entry_points.txt
kosciuszko_utils-0.2.0.dist-info/top_level.txt
kosciuszko_utils-0.2.0.dist-info/RECORD
