Metadata-Version: 2.1
Name: kosciuszko-utils
Version: 0.2.0
Summary: Library for managing kosciuszko vaults
Home-page: https://git.sr.ht/~happy_shredder/kosciuszko-utils
Author: happy_shredder
Author-email: contact@etage.io
License: UNKNOWN
Platform: UNKNOWN
Classifier: Programming Language :: Python :: 3
Classifier: License :: OSI Approved :: GNU General Public License v3 or later (GPLv3+)
Classifier: Operating System :: POSIX :: Linux
Classifier: Topic :: Security :: Cryptography
Classifier: Intended Audience :: End Users/Desktop
Classifier: Environment :: Console
Classifier: Development Status :: 3 - Alpha
Requires-Python: >=3.7
Requires-Dist: libkosciuszko
